CHANGES.txt
LICENSE.txt
MANIFEST.in
README.txt
setup.py
js/__init__.py
js.jqueryui.egg-info/PKG-INFO
js.jqueryui.egg-info/SOURCES.txt
js.jqueryui.egg-info/dependency_links.txt
js.jqueryui.egg-info/entry_points.txt
js.jqueryui.egg-info/namespace_packages.txt
js.jqueryui.egg-info/not-zip-safe
js.jqueryui.egg-info/requires.txt
js.jqueryui.egg-info/top_level.txt
js/jqueryui/__init__.py
js/jqueryui/download.py
js/jqueryui/test_jqueryui.txt
js/jqueryui/resources/themes/base/.DS_Store
js/jqueryui/resources/themes/base/jquery-ui.css
js/jqueryui/resources/themes/base/jquery-ui.min.css
js/jqueryui/resources/themes/base/jquery.ui.accordion.css
js/jqueryui/resources/themes/base/jquery.ui.all.css
js/jqueryui/resources/themes/base/jquery.ui.autocomplete.css
js/jqueryui/resources/themes/base/jquery.ui.base.css
js/jqueryui/resources/themes/base/jquery.ui.button.css
js/jqueryui/resources/themes/base/jquery.ui.core.css
js/jqueryui/resources/themes/base/jquery.ui.datepicker.css
js/jqueryui/resources/themes/base/jquery.ui.dialog.css
js/jqueryui/resources/themes/base/jquery.ui.progressbar.css
js/jqueryui/resources/themes/base/jquery.ui.resizable.css
js/jqueryui/resources/themes/base/jquery.ui.selectable.css
js/jqueryui/resources/themes/base/jquery.ui.slider.css
js/jqueryui/resources/themes/base/jquery.ui.tabs.css
js/jqueryui/resources/themes/base/jquery.ui.theme.css
js/jqueryui/resources/themes/base/images/ui-bg_flat_0_aaaaaa_40x100.png
js/jqueryui/resources/themes/base/images/ui-bg_flat_75_ffffff_40x100.png
js/jqueryui/resources/themes/base/images/ui-bg_glass_55_fbf9ee_1x400.png
js/jqueryui/resources/themes/base/images/ui-bg_glass_65_ffffff_1x400.png
js/jqueryui/resources/themes/base/images/ui-bg_glass_75_dadada_1x400.png
js/jqueryui/resources/themes/base/images/ui-bg_glass_75_e6e6e6_1x400.png
js/jqueryui/resources/themes/base/images/ui-bg_glass_95_fef1ec_1x400.png
js/jqueryui/resources/themes/base/images/ui-bg_highlight-soft_75_cccccc_1x100.png
js/jqueryui/resources/themes/base/images/ui-icons_222222_256x240.png
js/jqueryui/resources/themes/base/images/ui-icons_2e83ff_256x240.png
js/jqueryui/resources/themes/base/images/ui-icons_454545_256x240.png
js/jqueryui/resources/themes/base/images/ui-icons_888888_256x240.png
