Metadata-Version: 1.0
Name: js.jqueryui
Version: 1.8.24
Summary: fanstatic jQuery UI.
Home-page: UNKNOWN
Author: Fanstatic Developers
Author-email: fanstatic@googlegroups.com
License: BSD
Platform: UNKNOWN
